dj_cache/__init__.py
dj_cache/apps.py
dj_cache/decorators.py
dj_cache/models.py
dj_cache/migrations/0001_initial.py
dj_cache/migrations/__init__.py
dj_cache-0.1.dist-info/METADATA
dj_cache-0.1.dist-info/WHEEL
dj_cache-0.1.dist-info/top_level.txt
dj_cache-0.1.dist-info/RECORD
